{
  "type": "Bank",
"data": [
 {
   "id": 1,
   "Transaction Date": "",
   "date": "01/06/2024",
   "narration": "Opening Balance",
   "Type": "",
   "debit": 0,
   "credit": 0,
   "balance": 22558664.47
 },
 {
   "id": 2,
   "Transaction Date": "03/06/2024",
   "date": "03/06/2024",
   "narration": "FEE ON EB AIICO CAP TRAINING FEE 0000122406032010 FEE ON EB AIICO 74418021987441802200 GTB",
   "Type": "MSC",
   "debit": 50,
   "credit": 0,
   "balance": 22558614.47
 },
 {
   "id": 3,
   "Transaction Date": "03/06/2024",
   "date": "03/06/2024",
   "narration": "VAT FEE ON EB AIICO CAP TRAINING F 0000122406032010 VAT FEE ON EB AI 74418021987441802200 GTB",
   "Type": "MSC",
   "debit": 3.75,
   "credit": 0,
   "balance": 22558610.72
 },
 {
   "id": 4,
   "Transaction Date": "03/06/2024",
   "date": "03/06/2024",
   "narration": "FEE ON EB AIICO CAP  8  PYT   B744 0000122406032010 FEE ON EB AIICO 74418021987441802201 UBA",
   "Type": "MSC",
   "debit": 50,
   "credit": 0,
   "balance": 22558560.72
 },
 {
   "id": 5,
   "Transaction Date": "03/06/2024",
   "date": "03/06/2024",
   "narration": "VAT FEE ON EB AIICO CAP  8  PYT 0000122406032010 VAT FEE ON EB AI 74418021987441802201 UBA",
   "Type": "MSC",
   "debit": 3.75,
   "credit": 0,
   "balance": 22558556.97
 },
 {
   "id": 6,
   "Transaction Date": "03/06/2024",
   "date": "03/06/2024",
   "narration": "FEE ON EB TRYRE AND BREAKPAD REPL 0000122406032010 FEE ON EB TRYRE 74418021987441802203 ZENITH",
   "Type": "MSC",
   "debit": 50,
   "credit": 0,
   "balance": 22558506.97
 },
 {
   "id": 7,
   "Transaction Date": "03/06/2024",
   "date": "03/06/2024",
   "narration": "VAT FEE ON EB TRYRE AND BREAKPAD R 0000122406032010 VAT FEE ON EB TR 74418021987441802203 ZENITH",
   "Type": "MSC",
   "debit": 3.75,
   "credit": 0,
   "balance": 22558503.22
 },
 {
   "id": 8,
   "Transaction Date": "03/06/2024",
   "date": "03/06/2024",
   "narration": "FEE ON EB POOL CAR REPAIRS PYT   B 0000122406032010 FEE ON EB POOL C 74418021987441802202 ZENITH",
   "Type": "MSC",
   "debit": 50,
   "credit": 0,
   "balance": 22558453.22
 },
 {
   "id": 9,
   "Transaction Date": "03/06/2024",
   "date": "03/06/2024",
   "narration": "VAT FEE ON EB POOL CAR REPAIRS PYT 0000122406032010 VAT FEE ON EB PO 74418021987441802202 ZENITH",
   "Type": "MSC",
   "debit": 3.75,
   "credit": 0,
   "balance": 22558449.47
 },
 {
   "id": 10,
   "Transaction Date": "03/06/2024",
   "date": "03/06/2024",
   "narration": "EB REGULATORY COMP  TRAINI   B7441 0000122406032010 EB REGULATORY CO RBX 74418021987441802200 GTB DATAPRO LIMITED",
   "Type": "MSC",
   "debit": 410000,
   "credit": 0,
   "balance": 22148449.47
 },
 {
   "id": 11,
   "Transaction Date": "03/06/2024",
   "date": "03/06/2024",
   "narration": "EB AIICO CAP  8  PYT   B7441802198 0000122406032010 EB AIICO CAP  8 RBX 74418021987441802201 UBA PELLY -SIMRAN NIGERIA",
   "Type": "MSC",
   "debit": 419840,
   "credit": 0,
   "balance": 21728609.47
 },
 {
   "id": 12,
   "Transaction Date": "03/06/2024",
   "date": "03/06/2024",
   "narration": "EB POOL CAR REPAIRS PYT   B7441802 0000122406032010 EB POOL CAR REPA RBX 74418021987441802202 ZENITH OTTOXPRESS LIMITED",
   "Type": "MSC",
   "debit": 639040,
   "credit": 0,
   "balance": 21089569.47
 },
 {
   "id": 13,
   "Transaction Date": "03/06/2024",
   "date": "03/06/2024",
   "narration": "EB TRYRE AND BREAKPAD REPL   B7441 0000122406032010 EB TRYRE AND BRE RBX 74418021987441802203 ZENITH CFAO MOTORS NIGERI",
   "Type": "MSC",
   "debit": 176300,
   "credit": 0,
   "balance": 20913269.47
 },
 {
   "id": 14,
   "Transaction Date": "05/06/2024",
   "date": "05/06/2024",
   "narration": "FEE ON EB FLIGHT REIMBURSEMENT   B 0000122406050915 FEE ON EB FLIGHT 75753044017575304403 GTB",
   "Type": "MSC",
   "debit": 50,
   "credit": 0,
   "balance": 20913219.47
 },
 {
   "id": 15,
   "Transaction Date": "05/06/2024",
   "date": "05/06/2024",
   "narration": "VAT FEE ON EB FLIGHT REIMBURSEMENT 0000122406050915 VAT FEE ON EB FL 75753044017575304403 GTB",
   "Type": "MSC",
   "debit": 3.75,
   "credit": 0,
   "balance": 20913215.72
 },
 {
   "id": 16,
   "Transaction Date": "05/06/2024",
   "date": "05/06/2024",
   "narration": "EB MD S FLIGHT REIMBURSEME   B7575 0000122406050915 EB MD S FLIGHT R RBX 75753044017575304403 GTB ADEMOLA  OLUFEMI CHRI",
   "Type": "MSC",
   "debit": 487000,
   "credit": 0,
   "balance": 20426215.72
 },
 {
   "id": 17,
   "Transaction Date": "05/06/2024",
   "date": "05/06/2024",
   "narration": "FEE ON EB AIICO CAP  2YR RENT   B7 0000122406051035 FEE ON EB AIICO 75801033287580103332 UBN",
   "Type": "MSC",
   "debit": 50,
   "credit": 0,
   "balance": 20426165.72
 },
 {
   "id": 18,
   "Transaction Date": "05/06/2024",
   "date": "05/06/2024",
   "narration": "VAT FEE ON EB AIICO CAP  2YR RENT 0000122406051035 VAT FEE ON EB AI 75801033287580103332 UBN",
   "Type": "MSC",
   "debit": 3.75,
   "credit": 0,
   "balance": 20426161.97
 },
 {
   "id": 19,
   "Transaction Date": "05/06/2024",
   "date": "05/06/2024",
   "narration": "EB 2 YR RENT FOR PH SPACE   B75801 0000122406051035 EB 2 YR RENT FOR RBX 75801033287580103332 UBN OSAS AND OSEJI",
   "Type": "MSC",
   "debit": 10550000,
   "credit": 0,
   "balance": 9876161.97
 },
 {
   "id": 20,
   "Transaction Date": "05/06/2024",
   "date": "05/06/2024",
   "narration": "FEE ON EB SERVICING OF GGE311GR 0000122406051045 FEE ON EB SERVIC 75807041027580704104 WEMA",
   "Type": "MSC",
   "debit": 50,
   "credit": 0,
   "balance": 9876111.97
 },
 {
   "id": 21,
   "Transaction Date": "05/06/2024",
   "date": "05/06/2024",
   "narration": "VAT FEE ON EB SERVICING OF GGE311G 0000122406051045 VAT FEE ON EB SE 75807041027580704104 WEMA",
   "Type": "MSC",
   "debit": 3.75,
   "credit": 0,
   "balance": 9876108.22
 },
 {
   "id": 22,
   "Transaction Date": "05/06/2024",
   "date": "05/06/2024",
   "narration": "EB SERVICING OF GGE311GR     B7580 0000122406051045 EB SERVICING OF RBX 75807041027580704104 WEMA HYUNDAI MOTORS NIGER",
   "Type": "MSC",
   "debit": 201720,
   "credit": 0,
   "balance": 9674388.22
 },
 {
   "id": 23,
   "Transaction Date": "05/06/2024",
   "date": "05/06/2024",
   "narration": "FEE ON EB MD S TRIP EXP    B759450 0000122406051435 FEE ON EB MD S T 75945032767594503278 GTB",
   "Type": "MSC",
   "debit": 50,
   "credit": 0,
   "balance": 9674338.22
 },
 {
   "id": 24,
   "Transaction Date": "05/06/2024",
   "date": "05/06/2024",
   "narration": "VAT FEE ON EB MD S TRIP EXP    B75 0000122406051435 VAT FEE ON EB MD 75945032767594503278 GTB",
   "Type": "MSC",
   "debit": 3.75,
   "credit": 0,
   "balance": 9674334.47
 },
 {
   "id": 25,
   "Transaction Date": "05/06/2024",
   "date": "05/06/2024",
   "narration": "EB MD S TRIP EXP    B7594503276T75 0000122406051435 EB MD S TRIP EXP RBX 75945032767594503278 GTB ADEMOLA  OLUFEMI CHRI",
   "Type": "MSC",
   "debit": 370000,
   "credit": 0,
   "balance": 9304334.47
 },
 {
   "id": 26,
   "Transaction Date": "05/06/2024",
   "date": "05/06/2024",
   "narration": "BVN Val portal W25052024 31052024 AIICO Capital Li BVN Val portal W",
   "Type": "TRF",
   "debit": 322.5,
   "credit": 0,
   "balance": 9304011.97
 },
 {
   "id": 27,
   "Transaction Date": "07/06/2024",
   "date": "07/06/2024",
   "narration": "FEE ON EB POOL CAR JJJ106DX REPAI 0000122406070835 FEE ON EB POOL C 77457031647745703168 ZENITH",
   "Type": "MSC",
   "debit": 50,
   "credit": 0,
   "balance": 9303961.97
 },
 {
   "id": 28,
   "Transaction Date": "07/06/2024",
   "date": "07/06/2024",
   "narration": "VAT FEE ON EB POOL CAR JJJ106DX RE 0000122406070835 VAT FEE ON EB PO 77457031647745703168 ZENITH",
   "Type": "MSC",
   "debit": 3.75,
   "credit": 0,
   "balance": 9303958.22
 },
 {
   "id": 29,
   "Transaction Date": "07/06/2024",
   "date": "07/06/2024",
   "narration": "EB POOL CAR JJJ106DX REPAI   B7745 0000122406070835 EB POOL CAR JJJ1 RBX 77457031647745703168 ZENITH IYKE MECHANICAL EN",
   "Type": "MSC",
   "debit": 301100,
   "credit": 0,
   "balance": 9002858.22
 },
 {
   "id": 30,
   "Transaction Date": "07/06/2024",
   "date": "07/06/2024",
   "narration": "FEE ON EB AIICO CAP VEHICLE SERVI 0000122406070845 FEE ON EB AIICO 77463032237746303226 ZENITH",
   "Type": "MSC",
   "debit": 50,
   "credit": 0,
   "balance": 9002808.22
 },
 {
   "id": 31,
   "Transaction Date": "07/06/2024",
   "date": "07/06/2024",
   "narration": "VAT FEE ON EB AIICO CAP VEHICLE SE 0000122406070845 VAT FEE ON EB AI 77463032237746303226 ZENITH",
   "Type": "MSC",
   "debit": 3.75,
   "credit": 0,
   "balance": 9002804.47
 },
 {
   "id": 32,
   "Transaction Date": "07/06/2024",
   "date": "07/06/2024",
   "narration": "FEE ON EB JUNE 2024 STAFF DATA RE 0000122406070845 FEE ON EB JUNE 2 77463032237746303225 GTB",
   "Type": "MSC",
   "debit": 50,
   "credit": 0,
   "balance": 9002754.47
 },
 {
   "id": 33,
   "Transaction Date": "07/06/2024",
   "date": "07/06/2024",
   "narration": "VAT FEE ON EB JUNE 2024 STAFF DATA 0000122406070845 VAT FEE ON EB JU 77463032237746303225 GTB",
   "Type": "MSC",
   "debit": 3.75,
   "credit": 0,
   "balance": 9002750.72
 },
 {
   "id": 34,
   "Transaction Date": "07/06/2024",
   "date": "07/06/2024",
   "narration": "EB MD S VEHICLE SERVICE   B7746303 0000122406070845 EB MD S VEHICLE RBX 77463032237746303226 ZENITH CFAO MOTORS NIGERI",
   "Type": "MSC",
   "debit": 164512.5,
   "credit": 0,
   "balance": 8838238.22
 },
 {
   "id": 35,
   "Transaction Date": "07/06/2024",
   "date": "07/06/2024",
   "narration": "EB JUNE 2024 STAFF DATA RE   B7746 0000122406070845 EB JUNE 2024 STA RBX 77463032237746303225 GTB OLAWUYI FAVOUR TOLUWA",
   "Type": "MSC",
   "debit": 291500,
   "credit": 0,
   "balance": 8546738.22
 },
 {
   "id": 36,
   "Transaction Date": "07/06/2024",
   "date": "07/06/2024",
   "narration": "NGN   USD ASSET FEB 2024 CUSTODY F  NGN   USD ASSET",
   "Type": "TRF",
   "debit": 130722.43,
   "credit": 0,
   "balance": 8416015.79
 },
 {
   "id": 37,
   "Transaction Date": "07/06/2024",
   "date": "07/06/2024",
   "narration": "CIB UTO Remittance of WHT on AIICO 0000042406071719 CIB UTO Remittan UBA NOMINEE -UBAT/AIICO MONEY MARKET FUND SUBSCRIP",
   "Type": "TRF",
   "debit": 0,
   "credit": 75000,
   "balance": 8491015.79
 },
 {
   "id": 38,
   "Transaction Date": "07/06/2024",
   "date": "07/06/2024",
   "narration": "CIB UTO Remittance of WHT on AIICO 0000042406071719 CIB UTO Remittan UBA NOMINEE -UBA TRUSTEES/MBA TRUST FUND",
   "Type": "TRF",
   "debit": 0,
   "credit": 75000,
   "balance": 8566015.79
 },
 {
   "id": 39,
   "Transaction Date": "07/06/2024",
   "date": "07/06/2024",
   "narration": "CIB UTO Newspaper Publicatio AIICO 0000042406071719 CIB UTO Newspape UBA NOMINEE -UBA TRUSTEES/MBA TRUST FUND",
   "Type": "TRF",
   "debit": 0,
   "credit": 367883.56,
   "balance": 8933899.35
 },
 {
   "id": 40,
   "Transaction Date": "07/06/2024",
   "date": "07/06/2024",
   "narration": "CIB UTO Newspaper Publicatio AIICO 0000042406071719 CIB UTO Newspape UBA NOMINEE -UBAT/AIICO MONEY MARKET FUND SUBSCRIP",
   "Type": "TRF",
   "debit": 0,
   "credit": 3754133.56,
   "balance": 12688032.91
 },
 {
   "id": 41,
   "Transaction Date": "07/06/2024",
   "date": "07/06/2024",
   "narration": "FEE ON EB AIICO CAP  3 3  PYT   B7 0000122406071845 FEE ON EB AIICO 77823034457782303447 UBA",
   "Type": "MSC",
   "debit": 50,
   "credit": 0,
   "balance": 12687982.91
 },
 {
   "id": 42,
   "Transaction Date": "07/06/2024",
   "date": "07/06/2024",
   "narration": "VAT FEE ON EB AIICO CAP  3 3  PYT 0000122406071845 VAT FEE ON EB AI 77823034457782303447 UBA",
   "Type": "MSC",
   "debit": 3.75,
   "credit": 0,
   "balance": 12687979.16
 },
 {
   "id": 43,
   "Transaction Date": "07/06/2024",
   "date": "07/06/2024",
   "narration": "EB AIICO CAP  3 3  PYT   B77823034 0000122406071845 EB AIICO CAP  3 RBX 77823034457782303447 UBA PELLY -SIMRAN NIGERIA",
   "Type": "MSC",
   "debit": 173184,
   "credit": 0,
   "balance": 12514795.16
 },
 {
   "id": 44,
   "Transaction Date": "11/06/2024",
   "date": "11/06/2024",
   "narration": "EB POOL CAR JJJ106DX REPAI   B7745 000012240607083503000862769260 EB POOL CAR JJJ1",
   "Type": "TRF",
   "debit": 0,
   "credit": 301100,
   "balance": 12815895.16
 },
 {
   "id": 45,
   "Transaction Date": "13-06-2024",
   "date": "13-06-2024",
   "narration": "FEE ON EB 20  BAL ON JJJJ266FQ RE 0000122406130905 FEE ON EB 20  BA 82659029338265902935 ZENITH",
   "Type": "MSC",
   "debit": 50,
   "credit": 0,
   "balance": 12815845.16
 },
 {
   "id": 46,
   "Transaction Date": "13-06-2024",
   "date": "13-06-2024",
   "narration": "VAT FEE ON EB 20  BAL ON JJJJ266FQ 0000122406130905 VAT FEE ON EB 20 82659029338265902935 ZENITH",
   "Type": "MSC",
   "debit": 3.75,
   "credit": 0,
   "balance": 12815841.41
 },
 {
   "id": 47,
   "Transaction Date": "13-06-2024",
   "date": "13-06-2024",
   "narration": "EB 20  BAL ON JJJJ266FQ RE   B8265 0000122406130905 EB 20  BAL ON JJ RBX 82659029338265902935 ZENITH OTTOXPRESS LIMITED",
   "Type": "MSC",
   "debit": 160510,
   "credit": 0,
   "balance": 12655331.41
 },
 {
   "id": 48,
   "Transaction Date": "13-06-2024",
   "date": "13-06-2024",
   "narration": "FEE ON EB AIICO CAP MEMBERSHIP FEE 0000122406130905 FEE ON EB AIICO 82659029278265902931 UBN",
   "Type": "MSC",
   "debit": 50,
   "credit": 0,
   "balance": 12655281.41
 },
 {
   "id": 49,
   "Transaction Date": "13-06-2024",
   "date": "13-06-2024",
   "narration": "VAT FEE ON EB AIICO CAP MEMBERSHIP 0000122406130905 VAT FEE ON EB AI 82659029278265902931 UBN",
   "Type": "MSC",
   "debit": 3.75,
   "credit": 0,
   "balance": 12655277.66
 },
 {
   "id": 50,
   "Transaction Date": "13-06-2024",
   "date": "13-06-2024",
   "narration": "EB CRC MEMBERSHIP FEE   B826590292 0000122406130905 EB CRC MEMBERSHI RBX 82659029278265902931 UBN CRC CREDIT BUREAU",
   "Type": "MSC",
   "debit": 209625,
   "credit": 0,
   "balance": 12445652.66
 },
 {
   "id": 51,
   "Transaction Date": "13-06-2024",
   "date": "13-06-2024",
   "narration": "FEE ON EB AIICO CAP MEMBERSHIP FEE 0000122406130935 FEE ON EB AIICO 82677025488267702552 GTB",
   "Type": "MSC",
   "debit": 50,
   "credit": 0,
   "balance": 12445602.66
 },
 {
   "id": 52,
   "Transaction Date": "13-06-2024",
   "date": "13-06-2024",
   "narration": "VAT FEE ON EB AIICO CAP MEMBERSHIP 0000122406130935 VAT FEE ON EB AI 82677025488267702552 GTB",
   "Type": "MSC",
   "debit": 3.75,
   "credit": 0,
   "balance": 12445598.91
 },
 {
   "id": 53,
   "Transaction Date": "13-06-2024",
   "date": "13-06-2024",
   "narration": "EB MEMBERSHIP FEE FIRST CE   B8267 0000122406130935 EB MEMBERSHIP FE RBX 82677025488267702552 GTB FIRSTCENTRAL CREDIT B",
   "Type": "MSC",
   "debit": 243750,
   "credit": 0,
   "balance": 12201848.91
 },
 {
   "id": 54,
   "Transaction Date": "13-06-2024",
   "date": "13-06-2024",
   "narration": "CIB UTO AMMF REDEMPTION AIICO CAPI 0000042406131844 CIB UTO AMMF RED UBA NOMINEE -UBAT/AIICO MONEY MARKET FUND SUBSCRIP",
   "Type": "TRF",
   "debit": 0,
   "credit": 80000000,
   "balance": 92201848.91
 },
 {
   "id": 55,
   "Transaction Date": "14-06-2024",
   "date": "14-06-2024",
   "narration": "REV EB POOL CAR JJJ106DX REPAI   B 000012240607083503000862769260 REV EB POOL CAR",
   "Type": "TRF",
   "debit": 0,
   "credit": 53.75,
   "balance": 92201902.66
 },
 {
   "id": 56,
   "Transaction Date": "14-06-2024",
   "date": "14-06-2024",
   "narration": "00295965541406202411030430994 INFR 1406202411030430 0029596554140620 AIICO CAPITAL LIMITED-MANAGED FUND",
   "Type": "TRF",
   "debit": 0,
   "credit": 7148663.19,
   "balance": 99350565.85
 },
 {
   "id": 57,
   "Transaction Date": "14-06-2024",
   "date": "14-06-2024",
   "narration": "ITMS AMMF AND ABF VAT CHARGES AMMF AND ABF VAT ITMS AMMF AND AB FNX IFT 1306202415500429628 1306202415500429629",
   "Type": "TRF",
   "debit": 2541259.03,
   "credit": 0,
   "balance": 96809306.82
 },
 {
   "id": 58,
   "Transaction Date": "14-06-2024",
   "date": "14-06-2024",
   "narration": "00295964371406202411030430990 REFU 1406202411030430 0029596437140620 AIICO CAPITAL LIMITED -THIRD PARTY ACCOUNT",
   "Type": "TRF",
   "debit": 0,
   "credit": 9490160.17,
   "balance": 106299466.99
 },
 {
   "id": 59,
   "Transaction Date": "14-06-2024",
   "date": "14-06-2024",
   "narration": "ITMS ITF Reimbursement training ITF Reimbursemen ITMS ITF Reimbur FNX IFT 1406202411030430991 1406202411030430992",
   "Type": "TRF",
   "debit": 100000,
   "credit": 0,
   "balance": 106199466.99
 },
 {
   "id": 60,
   "Transaction Date": "14-06-2024",
   "date": "14-06-2024",
   "narration": "FEE ON EB AIICO CAPITAL BOOK PYT 0000122406141335 FEE ON EB AIICO 83685047848368504787 ZENITH",
   "Type": "MSC",
   "debit": 25,
   "credit": 0,
   "balance": 106199441.99
 },
 {
   "id": 61,
   "Transaction Date": "14-06-2024",
   "date": "14-06-2024",
   "narration": "VAT FEE ON EB AIICO CAPITAL BOOK P 0000122406141335 VAT FEE ON EB AI 83685047848368504787 ZENITH",
   "Type": "MSC",
   "debit": 1.88,
   "credit": 0,
   "balance": 106199440.11
 },
 {
   "id": 62,
   "Transaction Date": "14-06-2024",
   "date": "14-06-2024",
   "narration": "FEE ON EB 2 STAFF BOND TRAINING 0000122406141335 FEE ON EB 2 STAF 83685047848368504786 UBA",
   "Type": "MSC",
   "debit": 50,
   "credit": 0,
   "balance": 106199390.11
 },
 {
   "id": 63,
   "Transaction Date": "14-06-2024",
   "date": "14-06-2024",
   "narration": "VAT FEE ON EB 2 STAFF BOND TRAININ 0000122406141335 VAT FEE ON EB 2 83685047848368504786 UBA",
   "Type": "MSC",
   "debit": 3.75,
   "credit": 0,
   "balance": 106199386.36
 },
 {
   "id": 64,
   "Transaction Date": "14-06-2024",
   "date": "14-06-2024",
   "narration": "FEE ON EB AIICO CAPITAL ELECTRICI 0000122406141335 FEE ON EB AIICO 83685047848368504788 ECOBANK",
   "Type": "MSC",
   "debit": 50,
   "credit": 0,
   "balance": 106199336.36
 },
 {
   "id": 65,
   "Transaction Date": "14-06-2024",
   "date": "14-06-2024",
   "narration": "VAT FEE ON EB AIICO CAPITAL ELECTR 0000122406141335 VAT FEE ON EB AI 83685047848368504788 ECOBANK",
   "Type": "MSC",
   "debit": 3.75,
   "credit": 0,
   "balance": 106199332.61
 },
 {
   "id": 66,
   "Transaction Date": "14-06-2024",
   "date": "14-06-2024",
   "narration": "EB ABUJA OFFICE ELECTRICITY   B836 0000122406141335 EB ABUJA OFFICE RBX 83685047848368504788 ECOBANK THE STATEMENT HOT",
   "Type": "MSC",
   "debit": 90000,
   "credit": 0,
   "balance": 106109332.61
 },
 {
   "id": 67,
   "Transaction Date": "14-06-2024",
   "date": "14-06-2024",
   "narration": "EB ANTI CORRUPTION BOOKLET   B8368 0000122406141335 EB ANTI CORRUPTI RBX 83685047848368504787 ZENITH CONTROL  amp  SURV",
   "Type": "MSC",
   "debit": 30000,
   "credit": 0,
   "balance": 106079332.61
 },
 {
   "id": 68,
   "Transaction Date": "14-06-2024",
   "date": "14-06-2024",
   "narration": "EB 2 STAFF BOND TRAINING   B836850 0000122406141335 EB 2 STAFF BOND RBX 83685047848368504786 UBA CHARTERED INSTITUTE O",
   "Type": "MSC",
   "debit": 180000,
   "credit": 0,
   "balance": 105899332.61
 },
 {
   "id": 69,
   "Transaction Date": "14-06-2024",
   "date": "14-06-2024",
   "narration": "BVN val portal W01062024 07062024 AIICO Capital Li BVN val portal W",
   "Type": "TRF",
   "debit": 112.88,
   "credit": 0,
   "balance": 105899219.73
 },
 {
   "id": 70,
   "Transaction Date": "14-06-2024",
   "date": "14-06-2024",
   "narration": "FEE ON EB PART PAYMENT FOR IMPLEM 0000122406141535 FEE ON EB PART P 83757032098375703216 VFD MICROFINANCE",
   "Type": "MSC",
   "debit": 50,
   "credit": 0,
   "balance": 105899169.73
 },
 {
   "id": 71,
   "Transaction Date": "14-06-2024",
   "date": "14-06-2024",
   "narration": "VAT FEE ON EB PART PAYMENT FOR IMP 0000122406141535 VAT FEE ON EB PA 83757032098375703216 VFD MICROFINANCE",
   "Type": "MSC",
   "debit": 3.75,
   "credit": 0,
   "balance": 105899165.98
 },
 {
   "id": 72,
   "Transaction Date": "14-06-2024",
   "date": "14-06-2024",
   "narration": "FEE ON EB TRANSFER   B8375703213T8 0000122406141535 FEE ON EB TRANSF 83757032138375703215 OPTIMUS BANK",
   "Type": "MSC",
   "debit": 50,
   "credit": 0,
   "balance": 105899115.98
 },
 {
   "id": 73,
   "Transaction Date": "14-06-2024",
   "date": "14-06-2024",
   "narration": "VAT FEE ON EB TRANSFER   B83757032 0000122406141535 VAT FEE ON EB TR 83757032138375703215 OPTIMUS BANK",
   "Type": "MSC",
   "debit": 3.75,
   "credit": 0,
   "balance": 105899112.23
 },
 {
   "id": 74,
   "Transaction Date": "14-06-2024",
   "date": "14-06-2024",
   "narration": "FEE ON EB DISBURSEMENT   B83757032 0000122406141535 FEE ON EB DISBUR 83757032118375703217 GTB",
   "Type": "MSC",
   "debit": 50,
   "credit": 0,
   "balance": 105899062.23
 },
 {
   "id": 75,
   "Transaction Date": "14-06-2024",
   "date": "14-06-2024",
   "narration": "VAT FEE ON EB DISBURSEMENT   B8375 0000122406141535 VAT FEE ON EB DI 83757032118375703217 GTB",
   "Type": "MSC",
   "debit": 3.75,
   "credit": 0,
   "balance": 105899058.48
 },
 {
   "id": 76,
   "Transaction Date": "14-06-2024",
   "date": "14-06-2024",
   "narration": "EB PART PAYMENT FOR IMPLEM   B8375 0000122406141535 EB PART PAYMENT RBX 83757032098375703216 VFD MICROFINANCE SIMPLEX",
   "Type": "MSC",
   "debit": 4875000,
   "credit": 0,
   "balance": 101024058.48
 },
 {
   "id": 77,
   "Transaction Date": "14-06-2024",
   "date": "14-06-2024",
   "narration": "EB TRANSFER   B8375703213T83757032 0000122406141535 EB TRANSFER   B8 RBX 83757032138375703215 OPTIMUS BANK DEALMAKERS E",
   "Type": "MSC",
   "debit": 22425000,
   "credit": 0,
   "balance": 78599058.48
 },
 {
   "id": 78,
   "Transaction Date": "14-06-2024",
   "date": "14-06-2024",
   "narration": "EB DISBURSEMENT   B8375703211T8375 0000122406141535 EB DISBURSEMENT RBX 83757032118375703217 GTB ADENIYI",
   "Type": "MSC",
   "debit": 5000000,
   "credit": 0,
   "balance": 73599058.48
 },
 {
   "id": 79,
   "Transaction Date": "14-06-2024",
   "date": "14-06-2024",
   "narration": "TRN IFO REMITA CHARGES  TRN IFO REMITA C",
   "Type": "TRF",
   "debit": 161.25,
   "credit": 0,
   "balance": 73598897.23
 },
 {
   "id": 80,
   "Transaction Date": "14-06-2024",
   "date": "14-06-2024",
   "narration": "FEE ON IBR POOL CAR JJJ106DX REPAR 0000122406141726 FEE ON IBR POOL 172107401658C874017 ZENITH",
   "Type": "MSC",
   "debit": 50,
   "credit": 0,
   "balance": 73598847.23
 },
 {
   "id": 81,
   "Transaction Date": "14-06-2024",
   "date": "14-06-2024",
   "narration": "VAT FEE ON IBR POOL CAR JJJ106DX R 0000122406141726 VAT FEE ON IBR P 172107401658C874017 ZENITH",
   "Type": "MSC",
   "debit": 3.75,
   "credit": 0,
   "balance": 73598843.48
 },
 {
   "id": 82,
   "Transaction Date": "14-06-2024",
   "date": "14-06-2024",
   "narration": "IBR POOL CAR JJJ106DX REPAR BALANC 0000122406141726 IBR POOL CAR JJJ RBX 172107401658C874017 ZENITH IYKE MECHANICAL ENG",
   "Type": "MSC",
   "debit": 301100,
   "credit": 0,
   "balance": 73297743.48
 },
 {
   "id": 83,
   "Transaction Date": "14-06-2024",
   "date": "14-06-2024",
   "narration": "FEE ON EB PAYMENT AS REIMBURSEMEN 0000122406141920 FEE ON EB PAYMEN 83892040818389204085 ACCESS",
   "Type": "MSC",
   "debit": 25,
   "credit": 0,
   "balance": 73297718.48
 },
 {
   "id": 84,
   "Transaction Date": "14-06-2024",
   "date": "14-06-2024",
   "narration": "VAT FEE ON EB PAYMENT AS REIMBURSE 0000122406141920 VAT FEE ON EB PA 83892040818389204085 ACCESS",
   "Type": "MSC",
   "debit": 1.88,
   "credit": 0,
   "balance": 73297716.6
 },
 {
   "id": 85,
   "Transaction Date": "14-06-2024",
   "date": "14-06-2024",
   "narration": "FEE ON EB DIASPORA FUND EOI AND S 0000122406141920 FEE ON EB DIASPO 83892040828389204086 FBN",
   "Type": "MSC",
   "debit": 50,
   "credit": 0,
   "balance": 73297666.6
 },
 {
   "id": 86,
   "Transaction Date": "14-06-2024",
   "date": "14-06-2024",
   "narration": "VAT FEE ON EB DIASPORA FUND EOI AN 0000122406141920 VAT FEE ON EB DI 83892040828389204086 FBN",
   "Type": "MSC",
   "debit": 3.75,
   "credit": 0,
   "balance": 73297662.85
 },
 {
   "id": 87,
   "Transaction Date": "14-06-2024",
   "date": "14-06-2024",
   "narration": "EB DIASPORA FUND EOI AND S   B8389 0000122406141920 EB DIASPORA FUND RBX 83892040828389204086 FBN NWACHUKWU IFEANYI STA",
   "Type": "MSC",
   "debit": 207000,
   "credit": 0,
   "balance": 73090662.85
 },
 {
   "id": 88,
   "Transaction Date": "14-06-2024",
   "date": "14-06-2024",
   "narration": "EB PAYMENT AS REIMBURSEMEN   B8389 0000122406141920 EB PAYMENT AS RE RBX 83892040818389204085 ACCESS MICHAEL OLUWATOSIN",
   "Type": "MSC",
   "debit": 37135,
   "credit": 0,
   "balance": 73053527.85
 },
 {
   "id": 89,
   "Transaction Date": "15-06-2024",
   "date": "15-06-2024",
   "narration": "ITMS AIICO CAPITAL OFFICE FURNITUR AIICO CAPITAL OF ITMS AIICO CAPIT FNX IFT 1506202414390936317 FTMQ15-06-24",
   "Type": "TRF",
   "debit": 3750250,
   "credit": 0,
   "balance": 69303277.85
 },
 {
   "id": 90,
   "Transaction Date": "15-06-2024",
   "date": "15-06-2024",
   "narration": "FEE ON EB PAYMENT FOR PURCHASE OF 0000122406151625 FEE ON EB PAYMEN 84651025108465102512 WEMA",
   "Type": "MSC",
   "debit": 50,
   "credit": 0,
   "balance": 69303227.85
 },
 {
   "id": 91,
   "Transaction Date": "15-06-2024",
   "date": "15-06-2024",
   "narration": "VAT FEE ON EB PAYMENT FOR PURCHASE 0000122406151625 VAT FEE ON EB PA 84651025108465102512 WEMA",
   "Type": "MSC",
   "debit": 3.75,
   "credit": 0,
   "balance": 69303224.1
 },
 {
   "id": 92,
   "Transaction Date": "15-06-2024",
   "date": "15-06-2024",
   "narration": "EB AIICO CAPITAL RECEPTION   B8465 0000122406151625 EB AIICO CAPITAL RBX 84651025108465102512 WEMA VAVA FURNITURE NIGER",
   "Type": "MSC",
   "debit": 500000,
   "credit": 0,
   "balance": 68803224.1
 },
 {
   "id": 93,
   "Transaction Date": "19-06-2024",
   "date": "19-06-2024",
   "narration": "FEE ON EB 50  BALANCE PAYMENT FOR 0000122406190915 FEE ON EB 50  BA 87849034858784903487 WEMA",
   "Type": "MSC",
   "debit": 50,
   "credit": 0,
   "balance": 68803174.1
 },
 {
   "id": 94,
   "Transaction Date": "19-06-2024",
   "date": "19-06-2024",
   "narration": "VAT FEE ON EB 50  BALANCE PAYMENT 0000122406190915 VAT FEE ON EB 50 87849034858784903487 WEMA",
   "Type": "MSC",
   "debit": 3.75,
   "credit": 0,
   "balance": 68803170.35
 },
 {
   "id": 95,
   "Transaction Date": "19-06-2024",
   "date": "19-06-2024",
   "narration": "EB AIICO CAPT  50  BALANCE   B8784 0000122406190915 EB AIICO CAPT  5 RBX 87849034858784903487 WEMA HYUNDAI MOTORS NIGER",
   "Type": "MSC",
   "debit": 556318.75,
   "credit": 0,
   "balance": 68246851.6
 },
 {
   "id": 96,
   "Transaction Date": "19-06-2024",
   "date": "19-06-2024",
   "narration": "NGN   USD ASSET MAR 2024 CUSTODY F  NGN   USD ASSET",
   "Type": "TRF",
   "debit": 86765.63,
   "credit": 0,
   "balance": 68160085.97
 },
 {
   "id": 97,
   "Transaction Date": "20-06-2024",
   "date": "20-06-2024",
   "narration": "ITMS WHT CAPITAL TO LIRS MAY  2024 WHT CAPITAL TO L ITMS WHT CAPITAL FNX IFT 1906202415220639851 1906202415220639853",
   "Type": "TRF",
   "debit": 103780,
   "credit": 0,
   "balance": 68056305.97
 },
 {
   "id": 98,
   "Transaction Date": "20-06-2024",
   "date": "20-06-2024",
   "narration": "ITMS WHT CAPITAL TO FIRS MAY  2024 WHT CAPITAL TO F ITMS WHT CAPITAL FNX IFT 1906202415220639851 1906202415220639852",
   "Type": "TRF",
   "debit": 588087.99,
   "credit": 0,
   "balance": 67468217.98
 },
 {
   "id": 99,
   "Transaction Date": "20-06-2024",
   "date": "20-06-2024",
   "narration": "BVN Val portal W08062024 14062024  BVN Val portal W",
   "Type": "TRF",
   "debit": 64.5,
   "credit": 0,
   "balance": 67468153.48
 },
 {
   "id": 100,
   "Transaction Date": "20-06-2024",
   "date": "20-06-2024",
   "narration": "FEE ON EB PAYMENT FOR RETURN FLIG 0000122406201705 FEE ON EB PAYMEN 88995132468899513248 GTB",
   "Type": "MSC",
   "debit": 50,
   "credit": 0,
   "balance": 67468103.48
 },
 {
   "id": 101,
   "Transaction Date": "20-06-2024",
   "date": "20-06-2024",
   "narration": "VAT FEE ON EB PAYMENT FOR RETURN F 0000122406201705 VAT FEE ON EB PA 88995132468899513248 GTB",
   "Type": "MSC",
   "debit": 3.75,
   "credit": 0,
   "balance": 67468099.73
 },
 {
   "id": 102,
   "Transaction Date": "20-06-2024",
   "date": "20-06-2024",
   "narration": "FEE ON EB HP PRO 240 G9 ALL IN ON 0000122406201705 FEE ON EB HP PRO 88995129478899512949 UBA",
   "Type": "MSC",
   "debit": 50,
   "credit": 0,
   "balance": 67468049.73
 },
 {
   "id": 103,
   "Transaction Date": "20-06-2024",
   "date": "20-06-2024",
   "narration": "VAT FEE ON EB HP PRO 240 G9 ALL IN 0000122406201705 VAT FEE ON EB HP 88995129478899512949 UBA",
   "Type": "MSC",
   "debit": 3.75,
   "credit": 0,
   "balance": 67468045.98
 },
 {
   "id": 104,
   "Transaction Date": "20-06-2024",
   "date": "20-06-2024",
   "narration": "EB AIICO CAP HP PRO 240 G9   B8899 0000122406201705 EB AIICO CAP HP RBX 88995129478899512949 UBA HIRI TECHNOLOGIES AND",
   "Type": "MSC",
   "debit": 738000,
   "credit": 0,
   "balance": 66730045.98
 },
 {
   "id": 105,
   "Transaction Date": "20-06-2024",
   "date": "20-06-2024",
   "narration": "EB PAYMENT FOR RETURN FLIG   B8899 0000122406201705 EB PAYMENT FOR R RBX 88995132468899513248 GTB OTESANYA MICHAEL OLUW",
   "Type": "MSC",
   "debit": 358200,
   "credit": 0,
   "balance": 66371845.98
 },
 {
   "id": 106,
   "Transaction Date": "21-06-2024",
   "date": "21-06-2024",
   "narration": "FEE ON EB COST OF LAPTOP REPAIRS 0000122406211415 FEE ON EB COST O 89757070388975707041 ZENITH",
   "Type": "MSC",
   "debit": 50,
   "credit": 0,
   "balance": 66371795.98
 },
 {
   "id": 107,
   "Transaction Date": "21-06-2024",
   "date": "21-06-2024",
   "narration": "VAT FEE ON EB COST OF LAPTOP REPAI 0000122406211415 VAT FEE ON EB CO 89757070388975707041 ZENITH",
   "Type": "MSC",
   "debit": 3.75,
   "credit": 0,
   "balance": 66371792.23
 },
 {
   "id": 108,
   "Transaction Date": "21-06-2024",
   "date": "21-06-2024",
   "narration": "FEE ON EB PAYMENT FOR THE REPLACE 0000122406211415 FEE ON EB PAYMEN 89757070368975707040 ZENITH",
   "Type": "MSC",
   "debit": 50,
   "credit": 0,
   "balance": 66371742.23
 },
 {
   "id": 109,
   "Transaction Date": "21-06-2024",
   "date": "21-06-2024",
   "narration": "VAT FEE ON EB PAYMENT FOR THE REPL 0000122406211415 VAT FEE ON EB PA 89757070368975707040 ZENITH",
   "Type": "MSC",
   "debit": 3.75,
   "credit": 0,
   "balance": 66371738.48
 },
 {
   "id": 110,
   "Transaction Date": "21-06-2024",
   "date": "21-06-2024",
   "narration": "EB AIICO CAPT COST OF LAPT   B8975 0000122406211415 EB AIICO CAPT CO RBX 89757070388975707041 ZENITH PC PLANET LIMITED",
   "Type": "MSC",
   "debit": 322875,
   "credit": 0,
   "balance": 66048863.48
 },
 {
   "id": 111,
   "Transaction Date": "21-06-2024",
   "date": "21-06-2024",
   "narration": "EB AIICIO CAP  PAYMENT FOR   B8975 0000122406211415 EB AIICIO CAP  P RBX 89757070368975707040 ZENITH CFAO MOTORS NIGERI",
   "Type": "MSC",
   "debit": 171175,
   "credit": 0,
   "balance": 65877688.48
 },
 {
   "id": 112,
   "Transaction Date": "22-06-2024",
   "date": "22-06-2024",
   "narration": "FEE ON EB PAYMENT FOR THE DELIVER 0000122406221205 FEE ON EB PAYMEN 90543037529054303754 ZENITH",
   "Type": "MSC",
   "debit": 25,
   "credit": 0,
   "balance": 65877663.48
 },
 {
   "id": 113,
   "Transaction Date": "22-06-2024",
   "date": "22-06-2024",
   "narration": "VAT FEE ON EB PAYMENT FOR THE DELI 0000122406221205 VAT FEE ON EB PA 90543037529054303754 ZENITH",
   "Type": "MSC",
   "debit": 1.88,
   "credit": 0,
   "balance": 65877661.6
 },
 {
   "id": 114,
   "Transaction Date": "22-06-2024",
   "date": "22-06-2024",
   "narration": "EB PAYMENT FOR THE DELIVER   B9054 0000122406221205 EB PAYMENT FOR T RBX 90543037529054303754 ZENITH EMMANUEL ELEOJO SA",
   "Type": "MSC",
   "debit": 36974.83,
   "credit": 0,
   "balance": 65840686.77
 },
 {
   "id": 115,
   "Transaction Date": "22-06-2024",
   "date": "22-06-2024",
   "narration": "FEE ON EB ABJ CLEANING SPACE   B90 0000122406221205 FEE ON EB ABJ CL 90543037559054303758 GTB",
   "Type": "MSC",
   "debit": 50,
   "credit": 0,
   "balance": 65840636.77
 },
 {
   "id": 116,
   "Transaction Date": "22-06-2024",
   "date": "22-06-2024",
   "narration": "VAT FEE ON EB ABJ CLEANING SPACE 0000122406221205 VAT FEE ON EB AB 90543037559054303758 GTB",
   "Type": "MSC",
   "debit": 3.75,
   "credit": 0,
   "balance": 65840633.02
 },
 {
   "id": 117,
   "Transaction Date": "22-06-2024",
   "date": "22-06-2024",
   "narration": "FEE ON EB 80  KITCHEN CABINET UPF 0000122406221205 FEE ON EB 80  KI 90543037559054303757 GTB",
   "Type": "MSC",
   "debit": 50,
   "credit": 0,
   "balance": 65840583.02
 },
 {
   "id": 118,
   "Transaction Date": "22-06-2024",
   "date": "22-06-2024",
   "narration": "VAT FEE ON EB 80  KITCHEN CABINET 0000122406221205 VAT FEE ON EB 80 90543037559054303757 GTB",
   "Type": "MSC",
   "debit": 3.75,
   "credit": 0,
   "balance": 65877684.73
 },
 {
   "id": 119,
   "Transaction Date": "22-06-2024",
   "date": "22-06-2024",
   "narration": "EB ABJ CLEANING SPACE   B905430375 0000122406221205 EB ABJ CLEANING RBX 90543037559054303758 GTB ALI LADIDI H",
   "Type": "MSC",
   "debit": 65000,
   "credit": 0,
   "balance": 65812684.73
 },
 {
   "id": 120,
   "Transaction Date": "22-06-2024",
   "date": "22-06-2024",
   "narration": "EB 80  KITCHEN CABINET UPF   B9054 0000122406221205 EB 80  KITCHEN C RBX 90543037559054303757 GTB GANIYU  KAZEEM AREMU",
   "Type": "MSC",
   "debit": 260000,
   "credit": 0,
   "balance": 65552684.73
 },
 {
   "id": 121,
   "Transaction Date": "24-06-2024",
   "date": "24-06-2024",
   "narration": "FEE ON EB 45MBPS FIBRE INTERNET 0000122406240550 FEE ON EB 45MBPS 92046024999204602501 KEYSTONE",
   "Type": "MSC",
   "debit": 50,
   "credit": 0,
   "balance": 65515529.27
 },
 {
   "id": 122,
   "Transaction Date": "24-06-2024",
   "date": "24-06-2024",
   "narration": "VAT FEE ON EB 45MBPS FIBRE INTERNE 0000122406240550 VAT FEE ON EB 45 92046024999204602501 KEYSTONE",
   "Type": "MSC",
   "debit": 3.75,
   "credit": 0,
   "balance": 65515525.52
 },
 {
   "id": 123,
   "Transaction Date": "24-06-2024",
   "date": "24-06-2024",
   "narration": "EB AIICO CAP   45MBPS FIBR   B9204 0000122406240550 EB AIICO CAP   4 RBX 92046024999204602501 KEYSTONE IPNX NIGERIA LTD",
   "Type": "MSC",
   "debit": 1269975,
   "credit": 0,
   "balance": 64245550.52
 },
 {
   "id": 124,
   "Transaction Date": "24-06-2024",
   "date": "24-06-2024",
   "narration": "TO STANBIC  AIICO CAPITAL LIMITED 0000232406240850 TO STANBIC  AIIC PROVIDUSBANK NIP",
   "Type": "TRF",
   "debit": 0,
   "credit": 85795715.37,
   "balance": 150041265.89
 },
 {
   "id": 125,
   "Transaction Date": "24-06-2024",
   "date": "24-06-2024",
   "narration": "FEE ON EB AIICO CAP 2 DRAWER FIRE 0000122406240905 FEE ON EB AIICO 92163038579216303859 ZENITH",
   "Type": "MSC",
   "debit": 50,
   "credit": 0,
   "balance": 150041215.89
 },
 {
   "id": 126,
   "Transaction Date": "24-06-2024",
   "date": "24-06-2024",
   "narration": "VAT FEE ON EB AIICO CAP 2 DRAWER F 0000122406240905 VAT FEE ON EB AI 92163038579216303859 ZENITH",
   "Type": "MSC",
   "debit": 3.75,
   "credit": 0,
   "balance": 150041212.14
 },
 {
   "id": 127,
   "Transaction Date": "24-06-2024",
   "date": "24-06-2024",
   "narration": "EB 2 DRAWER FIREPROOF SAFE   B9216 0000122406240905 EB 2 DRAWER FIRE RBX 92163038579216303859 ZENITH GUMIS AND COMPANY",
   "Type": "MSC",
   "debit": 1394400,
   "credit": 0,
   "balance": 148646812.14
 },
 {
   "id": 128,
   "Transaction Date": "24-06-2024",
   "date": "24-06-2024",
   "narration": "FEE ON EB ABUJA OFFICE ITEM PURCH 0000122406240905 FEE ON EB ABUJA 92163038579216303860 GTB",
   "Type": "MSC",
   "debit": 50,
   "credit": 0,
   "balance": 148646762.14
 },
 {
   "id": 129,
   "Transaction Date": "24-06-2024",
   "date": "24-06-2024",
   "narration": "VAT FEE ON EB ABUJA OFFICE ITEM PU 0000122406240905 VAT FEE ON EB AB 92163038579216303860 GTB",
   "Type": "MSC",
   "debit": 3.75,
   "credit": 0,
   "balance": 148646758.39
 },
 {
   "id": 130,
   "Transaction Date": "24-06-2024",
   "date": "24-06-2024",
   "narration": "EB ABUJA OFFICE ITEM PURCH   B9216 0000122406240905 EB ABUJA OFFICE RBX 92163038579216303860 GTB OTESANYA MICHAEL OLUW",
   "Type": "MSC",
   "debit": 747200,
   "credit": 0,
   "balance": 147899558.39
 },
 {
   "id": 131,
   "Transaction Date": "24-06-2024",
   "date": "24-06-2024",
   "narration": "REV EB 45MBPS FIBRE INTERNET     B 0000122406240550 REV EB 45MBPS FI RBX 92046024999204602501 KEYSTONE IPNX NIGERIA LTD",
   "Type": "TRF",
   "debit": 0,
   "credit": 1269975,
   "balance": 149169533.39
 },
 {
   "id": 132,
   "Transaction Date": "24-06-2024",
   "date": "24-06-2024",
   "narration": "REV EB 45MBPS FIBRE INTERNET     B 0000122406240550 REV EB 45MBPS FI RBX 92046024999204602501 KEYSTONE IPNX NIGERIA LTD",
   "Type": "TRF",
   "debit": 0,
   "credit": 53.75,
   "balance": 149169587.14
 },
 {
   "id": 133,
   "Transaction Date": "24-06-2024",
   "date": "24-06-2024",
   "narration": "FEE ON EB ABJ OFFICE TILES REPLAC 0000122406241455 FEE ON EB ABJ OF 92373045019237304503 ACCESS",
   "Type": "MSC",
   "debit": 25,
   "credit": 0,
   "balance": 149169562.14
 },
 {
   "id": 134,
   "Transaction Date": "24-06-2024",
   "date": "24-06-2024",
   "narration": "VAT FEE ON EB ABJ OFFICE TILES REP 0000122406241455 VAT FEE ON EB AB 92373045019237304503 ACCESS",
   "Type": "MSC",
   "debit": 1.88,
   "credit": 0,
   "balance": 149169560.26
 },
 {
   "id": 135,
   "Transaction Date": "24-06-2024",
   "date": "24-06-2024",
   "narration": "FEE ON EB GGE311GR ROADWORTHINESS 0000122406241455 FEE ON EB GGE311 92373045109237304512 GTB",
   "Type": "MSC",
   "debit": 25,
   "credit": 0,
   "balance": 149169535.26
 },
 {
   "id": 136,
   "Transaction Date": "24-06-2024",
   "date": "24-06-2024",
   "narration": "VAT FEE ON EB GGE311GR ROADWORTHIN 0000122406241455 VAT FEE ON EB GG 92373045109237304512 GTB",
   "Type": "MSC",
   "debit": 1.88,
   "credit": 0,
   "balance": 149169533.38
 },
 {
   "id": 137,
   "Transaction Date": "24-06-2024",
   "date": "24-06-2024",
   "narration": "EB AIICO CAP ABJ OFFICE TI   B9237 0000122406241455 EB AIICO CAP ABJ RBX 92373045019237304503 ACCESS JANET OMOWUMI AMOD",
   "Type": "MSC",
   "debit": 12000,
   "credit": 0,
   "balance": 149157533.38
 },
 {
   "id": 138,
   "Transaction Date": "24-06-2024",
   "date": "24-06-2024",
   "narration": "EB GGE311GR ROADWORTHINESS   B9237 0000122406241455 EB GGE311GR ROAD RBX 92373045109237304512 GTB UGOCHUKWU-UNAM VIVIAN",
   "Type": "MSC",
   "debit": 20000,
   "credit": 0,
   "balance": 149137533.38
 },
 {
   "id": 139,
   "Transaction Date": "25-06-2024",
   "date": "25-06-2024",
   "narration": "FEE ON EB  SOPHOS END POINT   SER 0000122406250815 FEE ON EB  SOPHO 92997061359299706142 FCMB",
   "Type": "MSC",
   "debit": 50,
   "credit": 0,
   "balance": 149137483.38
 },
 {
   "id": 140,
   "Transaction Date": "25-06-2024",
   "date": "25-06-2024",
   "narration": "VAT FEE ON EB  SOPHOS END POINT 0000122406250815 VAT FEE ON EB  S 92997061359299706142 FCMB",
   "Type": "MSC",
   "debit": 3.75,
   "credit": 0,
   "balance": 149137479.63
 },
 {
   "id": 141,
   "Transaction Date": "25-06-2024",
   "date": "25-06-2024",
   "narration": "FEE ON EB HP COLOR LASERJET PRO M 0000122406250815 FEE ON EB HP COL 92997061379299706141 UBA",
   "Type": "MSC",
   "debit": 50,
   "credit": 0,
   "balance": 149137429.63
 },
 {
   "id": 142,
   "Transaction Date": "25-06-2024",
   "date": "25-06-2024",
   "narration": "VAT FEE ON EB HP COLOR LASERJET PR 0000122406250815 VAT FEE ON EB HP 92997061379299706141 UBA",
   "Type": "MSC",
   "debit": 3.75,
   "credit": 0,
   "balance": 149137425.88
 },
 {
   "id": 143,
   "Transaction Date": "25-06-2024",
   "date": "25-06-2024",
   "narration": "EB  SOPHOS END POINT   SER   B9299 0000122406250815 EB  SOPHOS END P RBX 92997061359299706142 FCMB SUFFIX BUSINESS  SOL",
   "Type": "MSC",
   "debit": 25866858.4,
   "credit": 0,
   "balance": 123270567.48
 },
 {
   "id": 144,
   "Transaction Date": "25-06-2024",
   "date": "25-06-2024",
   "narration": "EB HP COLOR LASERJET PRO M   B9299 0000122406250815 EB HP COLOR LASE RBX 92997061379299706141 UBA HIRI TECHNOLOGIES AND",
   "Type": "MSC",
   "debit": 738000,
   "credit": 0,
   "balance": 122532567.48
 },
 {
   "id": 145,
   "Transaction Date": "25-06-2024",
   "date": "25-06-2024",
   "narration": "FEE ON EB JUNE ACCT FUNDING   B929 0000122406250815 FEE ON EB JUNE A 92997061399299706143 FCMB",
   "Type": "MSC",
   "debit": 50,
   "credit": 0,
   "balance": 122532517.48
 },
 {
   "id": 146,
   "Transaction Date": "25-06-2024",
   "date": "25-06-2024",
   "narration": "VAT FEE ON EB JUNE ACCT FUNDING 0000122406250815 VAT FEE ON EB JU 92997061399299706143 FCMB",
   "Type": "MSC",
   "debit": 3.75,
   "credit": 0,
   "balance": 122532513.73
 },
 {
   "id": 147,
   "Transaction Date": "25-06-2024",
   "date": "25-06-2024",
   "narration": "EB JUNE ACCT FUNDING   B9299706139 0000122406250815 EB JUNE ACCT FUN RBX 92997061399299706143 FCMB AIICO CAPITAL LIMITE",
   "Type": "MSC",
   "debit": 35000000,
   "credit": 0,
   "balance": 87532513.73
 },
 {
   "id": 148,
   "Transaction Date": "25-06-2024",
   "date": "25-06-2024",
   "narration": "FEE ON EB UNLIMITED ELITE ULTRA 0000122406251015 FEE ON EB UNLIMI 93069032829306903288 GTB",
   "Type": "MSC",
   "debit": 50,
   "credit": 0,
   "balance": 87532463.73
 },
 {
   "id": 149,
   "Transaction Date": "25-06-2024",
   "date": "25-06-2024",
   "narration": "VAT FEE ON EB UNLIMITED ELITE ULTR 0000122406251015 VAT FEE ON EB UN 93069032829306903288 GTB",
   "Type": "MSC",
   "debit": 3.75,
   "credit": 0,
   "balance": 87532459.98
 },
 {
   "id": 150,
   "Transaction Date": "25-06-2024",
   "date": "25-06-2024",
   "narration": "FEE ON EB AIICO CAP BALANCE PAYME 0000122406251015 FEE ON EB AIICO 93069032899306903291 UBA",
   "Type": "MSC",
   "debit": 50,
   "credit": 0,
   "balance": 87532409.98
 },
 {
   "id": 151,
   "Transaction Date": "25-06-2024",
   "date": "25-06-2024",
   "narration": "VAT FEE ON EB AIICO CAP BALANCE PA 0000122406251015 VAT FEE ON EB AI 93069032899306903291 UBA",
   "Type": "MSC",
   "debit": 3.75,
   "credit": 0,
   "balance": 87532406.23
 },
 {
   "id": 152,
   "Transaction Date": "25-06-2024",
   "date": "25-06-2024",
   "narration": "EB BALANCE PAYMENT FOR THE   B9306 0000122406251015 EB BALANCE PAYME RBX 93069032899306903291 UBA PELLY -SIMRAN NIGERIA",
   "Type": "MSC",
   "debit": 464535,
   "credit": 0,
   "balance": 87067871.23
 },
 {
   "id": 153,
   "Transaction Date": "25-06-2024",
   "date": "25-06-2024",
   "narration": "EB UNLIMITED ELITE ULTRA     B9306 0000122406251015 EB UNLIMITED ELI RBX 93069032829306903288 GTB GIFRA WIRELESS NETWOR",
   "Type": "MSC",
   "debit": 154100,
   "credit": 0,
   "balance": 86913771.23
 },
 {
   "id": 154,
   "Transaction Date": "25-06-2024",
   "date": "25-06-2024",
   "narration": "FEE ON EB 45MBPS FIBRE INTERNET 0000122406251045 FEE ON EB 45MBPS 93087063199308706321 KEYSTONE",
   "Type": "MSC",
   "debit": 50,
   "credit": 0,
   "balance": 86913721.23
 },
 {
   "id": 155,
   "Transaction Date": "25-06-2024",
   "date": "25-06-2024",
   "narration": "VAT FEE ON EB 45MBPS FIBRE INTERNE 0000122406251045 VAT FEE ON EB 45 93087063199308706321 KEYSTONE",
   "Type": "MSC",
   "debit": 3.75,
   "credit": 0,
   "balance": 86913717.48
 },
 {
   "id": 156,
   "Transaction Date": "25-06-2024",
   "date": "25-06-2024",
   "narration": "EB AIICO CAP   45MBPS FIBR   B9308 0000122406251045 EB AIICO CAP   4 RBX 93087063199308706321 KEYSTONE IPNX NIGERIA LTD",
   "Type": "MSC",
   "debit": 1269975,
   "credit": 0,
   "balance": 85643742.48
 },
 {
   "id": 157,
   "Transaction Date": "25-06-2024",
   "date": "25-06-2024",
   "narration": "FEE ON EB AIICO CAP PAYMENT FOR F 0000122406251250 FEE ON EB AIICO 93162050889316205092 ACCESS",
   "Type": "MSC",
   "debit": 50,
   "credit": 0,
   "balance": 85643692.48
 },
 {
   "id": 158,
   "Transaction Date": "25-06-2024",
   "date": "25-06-2024",
   "narration": "VAT FEE ON EB AIICO CAP PAYMENT FO 0000122406251250 VAT FEE ON EB AI 93162050889316205092 ACCESS",
   "Type": "MSC",
   "debit": 3.75,
   "credit": 0,
   "balance": 85643688.73
 },
 {
   "id": 159,
   "Transaction Date": "25-06-2024",
   "date": "25-06-2024",
   "narration": "EB PAYMENT FOR FMDQ REGIST   B9316 0000122406251250 EB PAYMENT FOR F RBX 93162050889316205092 ACCESS FMDQ SECURITIES EX",
   "Type": "MSC",
   "debit": 2010937.5,
   "credit": 0,
   "balance": 83632751.23
 },
 {
   "id": 160,
   "Transaction Date": "25-06-2024",
   "date": "25-06-2024",
   "narration": "FEE ON EB ELECTRIC UNITS FOR ABUJ 0000122406251550 FEE ON EB ELECTR 93270057929327005795 GTB",
   "Type": "MSC",
   "debit": 25,
   "credit": 0,
   "balance": 83632726.23
 },
 {
   "id": 161,
   "Transaction Date": "25-06-2024",
   "date": "25-06-2024",
   "narration": "VAT FEE ON EB ELECTRIC UNITS FOR A 0000122406251550 VAT FEE ON EB EL 93270057929327005795 GTB",
   "Type": "MSC",
   "debit": 1.88,
   "credit": 0,
   "balance": 83632724.35
 },
 {
   "id": 162,
   "Transaction Date": "25-06-2024",
   "date": "25-06-2024",
   "narration": "FEE ON EB AIICO CAP JUNE 2024 OUT 0000122406251550 FEE ON EB AIICO 93270057909327005794 GTB",
   "Type": "MSC",
   "debit": 50,
   "credit": 0,
   "balance": 83632674.35
 },
 {
   "id": 163,
   "Transaction Date": "25-06-2024",
   "date": "25-06-2024",
   "narration": "VAT FEE ON EB AIICO CAP JUNE 2024 0000122406251550 VAT FEE ON EB AI 93270057909327005794 GTB",
   "Type": "MSC",
   "debit": 3.75,
   "credit": 0,
   "balance": 83632670.6
 },
 {
   "id": 164,
   "Transaction Date": "25-06-2024",
   "date": "25-06-2024",
   "narration": "EB ELECTRIC UNITS FOR ABUJ   B9327 0000122406251550 EB ELECTRIC UNIT RBX 93270057929327005795 GTB OTESANYA MICHAEL OLUW",
   "Type": "MSC",
   "debit": 50000,
   "credit": 0,
   "balance": 83582670.6
 },
 {
   "id": 165,
   "Transaction Date": "25-06-2024",
   "date": "25-06-2024",
   "narration": "EB JUNE 2024 OUTSOURCED SA   B9327 0000122406251550 EB JUNE 2024 OUT RBX 93270057909327005794 GTB INCITE ENTERPRISESOUT",
   "Type": "MSC",
   "debit": 1192214.24,
   "credit": 0,
   "balance": 82390456.36
 },
 {
   "id": 166,
   "Transaction Date": "25-06-2024",
   "date": "25-06-2024",
   "narration": "NGN   USD ASSET APRIL 2024 CUSTODY  NGN   USD ASSET",
   "Type": "TRF",
   "debit": 49801.36,
   "credit": 0,
   "balance": 82340655
 },
 {
   "id": 167,
   "Transaction Date": "26-06-2024",
   "date": "26-06-2024",
   "narration": "FEE ON EB AIICO CAP TOYOTA LAND C 0000122406260915 FEE ON EB AIICO 93897051169389705118 ZENITH",
   "Type": "MSC",
   "debit": 50,
   "credit": 0,
   "balance": 82340605
 },
 {
   "id": 168,
   "Transaction Date": "26-06-2024",
   "date": "26-06-2024",
   "narration": "VAT FEE ON EB AIICO CAP TOYOTA LAN 0000122406260915 VAT FEE ON EB AI 93897051169389705118 ZENITH",
   "Type": "MSC",
   "debit": 3.75,
   "credit": 0,
   "balance": 82340601.25
 },
 {
   "id": 169,
   "Transaction Date": "26-06-2024",
   "date": "26-06-2024",
   "narration": "EB TOYOTA LAND CRUISER  AA   B9389 0000122406260915 EB TOYOTA LAND C RBX 93897051169389705118 ZENITH CFAO MOTORS NIGERI",
   "Type": "MSC",
   "debit": 204487.5,
   "credit": 0,
   "balance": 82136113.75
 },
 {
   "id": 170,
   "Transaction Date": "27-06-2024",
   "date": "27-06-2024",
   "narration": "ITMS Registration fees to SEC for Registration fee ITMS Registratio FNX IFT 2706202410393256666 EFOA27-06-24",
   "Type": "TRF",
   "debit": 10001236.25,
   "credit": 0,
   "balance": 72134877.5
 },
 {
   "id": 171,
   "Transaction Date": "27-06-2024",
   "date": "27-06-2024",
   "narration": "ITMS NITDEF   PTF 2024 YOA NITDEF   PTF 202 ITMS NITDEF   PT FNX IFT 2706202410345256664 QQXB27-06-24",
   "Type": "TRF",
   "debit": 6196789.8,
   "credit": 0,
   "balance": 65938087.7
 },
 {
   "id": 172,
   "Transaction Date": "27-06-2024",
   "date": "27-06-2024",
   "narration": "FEE ON EB DAILY PRICE PUBLICATION 0000122406271550 FEE ON EB DAILY 94998053009499805302 GTB",
   "Type": "MSC",
   "debit": 25,
   "credit": 0,
   "balance": 65938062.7
 },
 {
   "id": 173,
   "Transaction Date": "27-06-2024",
   "date": "27-06-2024",
   "narration": "VAT FEE ON EB DAILY PRICE PUBLICAT 0000122406271550 VAT FEE ON EB DA 94998053009499805302 GTB",
   "Type": "MSC",
   "debit": 1.88,
   "credit": 0,
   "balance": 65938060.82
 },
 {
   "id": 174,
   "Transaction Date": "27-06-2024",
   "date": "27-06-2024",
   "narration": "FEE ON EB AIICO CAP PAYMENT FOR B 0000122406271550 FEE ON EB AIICO 94998052989499805306 UBN",
   "Type": "MSC",
   "debit": 50,
   "credit": 0,
   "balance": 65938010.82
 },
 {
   "id": 175,
   "Transaction Date": "27-06-2024",
   "date": "27-06-2024",
   "narration": "VAT FEE ON EB AIICO CAP PAYMENT FO 0000122406271550 VAT FEE ON EB AI 94998052989499805306 UBN",
   "Type": "MSC",
   "debit": 3.75,
   "credit": 0,
   "balance": 65938007.07
 },
 {
   "id": 176,
   "Transaction Date": "27-06-2024",
   "date": "27-06-2024",
   "narration": "FEE ON EB PAYMENT FOR RENEWAL OF 0000122406271550 FEE ON EB PAYMEN 94998053039499805305 GTB",
   "Type": "MSC",
   "debit": 50,
   "credit": 0,
   "balance": 65937957.07
 },
 {
   "id": 177,
   "Transaction Date": "27-06-2024",
   "date": "27-06-2024",
   "narration": "VAT FEE ON EB PAYMENT FOR RENEWAL 0000122406271550 VAT FEE ON EB PA 94998053039499805305 GTB",
   "Type": "MSC",
   "debit": 3.75,
   "credit": 0,
   "balance": 65937953.32
 },
 {
   "id": 178,
   "Transaction Date": "27-06-2024",
   "date": "27-06-2024",
   "narration": "FEE ON EB PROFESSIONAL FEES FOR R 0000122406271550 FEE ON EB PROFES 94998052869499805288 ZENITH",
   "Type": "MSC",
   "debit": 50,
   "credit": 0,
   "balance": 65937903.32
 },
 {
   "id": 179,
   "Transaction Date": "27-06-2024",
   "date": "27-06-2024",
   "narration": "VAT FEE ON EB PROFESSIONAL FEES FO 0000122406271550 VAT FEE ON EB PR 94998052869499805288 ZENITH",
   "Type": "MSC",
   "debit": 3.75,
   "credit": 0,
   "balance": 65937899.57
 },
 {
   "id": 180,
   "Transaction Date": "27-06-2024",
   "date": "27-06-2024",
   "narration": "EB DAILY PRICE PUBLICATION   B9499 0000122406271550 EB DAILY PRICE P RBX 94998053009499805302 GTB FMANDATA PROTECT REGU",
   "Type": "MSC",
   "debit": 33043.35,
   "credit": 0,
   "balance": 65904856.22
 },
 {
   "id": 181,
   "Transaction Date": "27-06-2024",
   "date": "27-06-2024",
   "narration": "EB PAYMENT FOR BODY WORK O   B9499 0000122406271550 EB PAYMENT FOR B RBX 94998052989499805306 UBN MOMOH MICHAEL OSELAMA",
   "Type": "MSC",
   "debit": 336200,
   "credit": 0,
   "balance": 65568656.22
 },
 {
   "id": 182,
   "Transaction Date": "27-06-2024",
   "date": "27-06-2024",
   "narration": "EB PAYMENT FOR RENEWAL OF    B9499 0000122406271550 EB PAYMENT FOR R RBX 94998053039499805305 GTB OKEOWO",
   "Type": "MSC",
   "debit": 56000,
   "credit": 0,
   "balance": 65512656.22
 },
 {
   "id": 183,
   "Transaction Date": "27-06-2024",
   "date": "27-06-2024",
   "narration": "EB PROFESSIONAL FEES FOR R   B9499 0000122406271550 EB PROFESSIONAL RBX 94998052869499805288 ZENITH ASPIRE SOLICITORS",
   "Type": "MSC",
   "debit": 212500,
   "credit": 0,
   "balance": 65300156.22
 },
 {
   "id": 184,
   "Transaction Date": "27-06-2024",
   "date": "27-06-2024",
   "narration": "BVN Val Portal W15062024 21062024 AIICO Capital Li BVN Val Portal W",
   "Type": "TRF",
   "debit": 387,
   "credit": 0,
   "balance": 65299769.22
 },
 {
   "id": 185,
   "Transaction Date": "27-06-2024",
   "date": "27-06-2024",
   "narration": "0000460692MYQE27 06 24 PYT ON ACC MYQE27 06 24 PYT 0000460692MYQE27 CORDROS SECURITIES LIMITED - CLIENTS CURRENT ACCOU",
   "Type": "TRF",
   "debit": 0,
   "credit": 240080125.07,
   "balance": 305379894.29
 },
 {
   "id": 186,
   "Transaction Date": "28-06-2024",
   "date": "28-06-2024",
   "narration": "ITMS proceeds from GIN Equity Sale proceeds from GI ITMS proceeds fr FNX IFT 2806202412024860322 TTRY28-06-24",
   "Type": "TRF",
   "debit": 240080125.07,
   "credit": 0,
   "balance": 65299769.22
 },
 {
   "id": 187,
   "Transaction Date": "28-06-2024",
   "date": "28-06-2024",
   "narration": "FEE ON EB DATA CONTROLLER  PROCES 0000122406281755 FEE ON EB DATA C 95937037339593703735 GTB",
   "Type": "MSC",
   "debit": 50,
   "credit": 0,
   "balance": 65299719.22
 },
 {
   "id": 188,
   "Transaction Date": "28-06-2024",
   "date": "28-06-2024",
   "narration": "VAT FEE ON EB DATA CONTROLLER  PRO 0000122406281755 VAT FEE ON EB DA 95937037339593703735 GTB",
   "Type": "MSC",
   "debit": 3.75,
   "credit": 0,
   "balance": 65299715.47
 },
 {
   "id": 189,
   "Transaction Date": "28-06-2024",
   "date": "28-06-2024",
   "narration": "EB DATA CONTROLLER  PROCES   B9593 0000122406281755 EB DATA CONTROLL RBX 95937037339593703735 GTB IYANDA SEGUN E.",
   "Type": "MSC",
   "debit": 250161.25,
   "credit": 0,
   "balance": 65049554.22
 },
 {
   "id": 190,
   "Transaction Date": "",
   "date": "30-06-2024",
   "narration": "Closing Balance",
   "Type": "",
   "debit": 0,
   "credit": 0,
   "balance": 65049554.22
 }
]
}